{
  "a": {
    "name": "Alex",
    "bio": "Guns.lol сонирхогч, вэб хөгжүүлэгч",
    "avatar": "https://api.dicebear.com/7.x/pixel-art/svg?seed=Alex",
    "discord": "alex#1337",
    "instagram": "alex_on_insta",
    "github": "alexdev"
  },
  "d3vnmd": {
    "name": "D3vnmd",
    "bio": "Энэхүү biolink платформыг бүтээгч",
    "avatar": "https://api.dicebear.com/7.x/pixel-art/svg?seed=d3vnmd",
    "discord": "d3vnmd#0001",
    "instagram": "d3vnmd_insta",
    "github": "d3vnmd"
  }
}